anime_speaker_embedding/__init__.py
anime_speaker_embedding/model.py
anime_speaker_embedding-0.2.1.dist-info/METADATA
anime_speaker_embedding-0.2.1.dist-info/WHEEL
anime_speaker_embedding-0.2.1.dist-info/licenses/LICENSE
anime_speaker_embedding-0.2.1.dist-info/RECORD
