Metadata-Version: 2.4
Name: anime_speaker_embedding
Version: 0.2.1
Summary: Speaker embedding for anime speech domain based on ECAPA_TDNN
Project-URL: Homepage, https://github.com/litagin02/anime_speaker_embedding
Project-URL: Source, https://github.com/litagin02/anime_speaker_embedding
Project-URL: Tracker, https://github.com/litagin02/anime_speaker_embedding/issues
Author-email: litagin02 <litagin02@gmail.com>
License: MIT License
License-File: LICENSE
Classifier: Development Status :: 3 - Alpha
Classifier: Intended Audience :: Developers
Classifier: License :: OSI Approved :: GNU General Public License v3 or later (GPLv3+)
Classifier: Programming Language :: Python :: 3
Classifier: Programming Language :: Python :: 3 :: Only
Classifier: Programming Language :: Python :: 3.9
Classifier: Programming Language :: Python :: 3.10
Classifier: Programming Language :: Python :: 3.11
Classifier: Programming Language :: Python :: 3.12
Classifier: Topic :: Multimedia :: Sound/Audio :: Analysis
Classifier: Topic :: Scientific/Engineering :: Artificial Intelligence
Requires-Python: >=3.9
Requires-Dist: huggingface-hub
Requires-Dist: librosa
Requires-Dist: numpy
Requires-Dist: speechbrain>=1.0.0
Requires-Dist: torch
